jup_swap/__init__.py
jup_swap/api.py
jup_swap-0.1.6.dist-info/LICENSE
jup_swap-0.1.6.dist-info/METADATA
jup_swap-0.1.6.dist-info/WHEEL
jup_swap-0.1.6.dist-info/top_level.txt
jup_swap-0.1.6.dist-info/RECORD
