Metadata-Version: 2.1
Name: jup-swap
Version: 0.1.6
Summary: Jupiter Swap Api V6 Client
Author-email: "Matrix.Ye" <initsysctrl@outlook.com>
License: MIT
Project-URL: Homepage, https://github.com/MatrixYe/jup-swap
Keywords: jupiter,solana
Classifier: Programming Language :: Python :: 3
Classifier: License :: OSI Approved :: MIT License
Classifier: Operating System :: OS Independent
Requires-Python: >=3.6
License-File: LICENSE
Requires-Dist: requests ~=2.31.0
